odoo/addons/web_pwa_oca/README.rst
odoo/addons/web_pwa_oca/__init__.py
odoo/addons/web_pwa_oca/__manifest__.py
odoo/addons/web_pwa_oca/controllers/__init__.py
odoo/addons/web_pwa_oca/controllers/main.py
odoo/addons/web_pwa_oca/controllers/service_worker.py
odoo/addons/web_pwa_oca/i18n/es.po
odoo/addons/web_pwa_oca/i18n/es_AR.po
odoo/addons/web_pwa_oca/i18n/pt_BR.po
odoo/addons/web_pwa_oca/i18n/web_pwa_oca.pot
odoo/addons/web_pwa_oca/models/__init__.py
odoo/addons/web_pwa_oca/models/res_config_settings.py
odoo/addons/web_pwa_oca/readme/CONFIGURE.rst
odoo/addons/web_pwa_oca/readme/CONTRIBUTORS.rst
odoo/addons/web_pwa_oca/readme/DESCRIPTION.rst
odoo/addons/web_pwa_oca/readme/INSTALL.rst
odoo/addons/web_pwa_oca/readme/ROADMAP.rst
odoo/addons/web_pwa_oca/readme/USAGE.rst
odoo/addons/web_pwa_oca/static/description/icon.png
odoo/addons/web_pwa_oca/static/description/index.html
odoo/addons/web_pwa_oca/static/description/pwa.png
odoo/addons/web_pwa_oca/static/img/icons/icon-128x128.png
odoo/addons/web_pwa_oca/static/img/icons/icon-144x144.png
odoo/addons/web_pwa_oca/static/img/icons/icon-152x152.png
odoo/addons/web_pwa_oca/static/img/icons/icon-192x192.png
odoo/addons/web_pwa_oca/static/img/icons/icon-256x256.png
odoo/addons/web_pwa_oca/static/img/icons/icon-512x512.png
odoo/addons/web_pwa_oca/static/img/icons/odoo_logo.svg
odoo/addons/web_pwa_oca/static/src/js/pwa_manager.js
odoo/addons/web_pwa_oca/static/src/js/webclient.js
odoo/addons/web_pwa_oca/static/src/js/worker/jquery-sw-compat.js
odoo/addons/web_pwa_oca/static/src/js/worker/pwa.js
odoo/addons/web_pwa_oca/templates/assets.xml
odoo/addons/web_pwa_oca/tests/__init__.py
odoo/addons/web_pwa_oca/tests/test_web_pwa_oca_controller.py
odoo/addons/web_pwa_oca/views/res_config_settings_views.xml
odoo14_addon_web_pwa_oca-14.0.1.1.0.dist-info/METADATA
odoo14_addon_web_pwa_oca-14.0.1.1.0.dist-info/WHEEL
odoo14_addon_web_pwa_oca-14.0.1.1.0.dist-info/top_level.txt
odoo14_addon_web_pwa_oca-14.0.1.1.0.dist-info/RECORD
